dalf/__init__.py
dalf/admin.py
dalf/apps.py
dalf/static/admin/css/django_admin_list_filter.css
dalf/static/admin/js/django_admin_list_filter.js
dalf/templates/admin/filter/django_admin_list_filter.html
dalf/templates/admin/filter/django_admin_list_filter_ajax.html
dalf/templates/admin/filter/django_admin_list_filter_ajax_multi.html
dalf-0.7.1.dist-info/licenses/LICENSE
dalf-0.7.1.dist-info/METADATA
dalf-0.7.1.dist-info/WHEEL
dalf-0.7.1.dist-info/top_level.txt
dalf-0.7.1.dist-info/RECORD
