Metadata-Version: 2.4
Name: dalf
Version: 0.7.1
Summary: Dead simple autocompletion for Django admin list_filter with goodies.
Author-email: Uğur Özyılmazel <ugurozyilmazel@gmail.com>
License-Expression: MIT
Project-URL: Homepage, https://github.com/vigo/django-admin-list-filter
Project-URL: Repository, https://github.com/vigo/django-admin-list-filter
Project-URL: Issues, https://github.com/vigo/django-admin-list-filter/issues
Keywords: django,django admin,list filter
Classifier: Programming Language :: Python :: 3 :: Only
Classifier: Programming Language :: Python :: 3.11
Classifier: Programming Language :: Python :: 3.12
Classifier: Programming Language :: Python :: 3.13
Classifier: Programming Language :: Python :: 3.14
Classifier: Operating System :: OS Independent
Classifier: Framework :: Django :: 5.0
Classifier: Framework :: Django :: 5.1
Classifier: Framework :: Django :: 5.2
Classifier: Intended Audience :: Developers
Classifier: Development Status :: 5 - Production/Stable
Classifier: Natural Language :: English
Requires-Python: >=3.11
License-File: LICENSE
Provides-Extra: build
Requires-Dist: build; extra == "build"
Requires-Dist: twine; extra == "build"
Provides-Extra: dev
Requires-Dist: Django; extra == "dev"
Requires-Dist: pytest; extra == "dev"
Requires-Dist: pytest-django; extra == "dev"
Requires-Dist: pytest-factoryboy; extra == "dev"
Requires-Dist: pytest-cov; extra == "dev"
Dynamic: license-file
